addressbook/__init__.py
addressbook/about.py
addressbook/blank.db
addressbook/help.py
addressbook/main.py
addressbook/settings.py
addressbook/data/__init__.py
addressbook/data/create.py
addressbook/data/delete.py
addressbook/data/identifiers.py
addressbook/data/read.py
addressbook/data/update.py
addressbook/models/__init__.py
addressbook/models/addresses.py
addressbook/models/codes.py
addressbook/models/contacts.py
addressbook/models/identities.py
addressbook/models/people.py
addressbook/models/recordeventtypes.py
addressbook/ui/__init__.py
addressbook/ui/about_ui.py
addressbook/ui/address_ui.py
addressbook/ui/comment_ui.py
addressbook/ui/controls.py
addressbook/ui/dashboard_ui.py
addressbook/ui/email_ui.py
addressbook/ui/help_ui.py
addressbook/ui/identity_ui.py
addressbook/ui/person_ui.py
addressbook/ui/phone_ui.py
addressbook/ui/relation_ui.py
addressbook/ui/rules.py
addressbook-1.0.1.dist-info/DESCRIPTION.rst
addressbook-1.0.1.dist-info/METADATA
addressbook-1.0.1.dist-info/RECORD
addressbook-1.0.1.dist-info/WHEEL
addressbook-1.0.1.dist-info/metadata.json
addressbook-1.0.1.dist-info/top_level.txt
