Metadata-Version: 1.1
Name: addressbook
Version: 1.0.1
Summary: A simple stand-alone address book for keeping track of people's addresses, contact information, identification, and relationships.
Home-page: http://www.adamyork.com/addressbook
Author: Adam S. York
Author-email: code@adamyork.com
License: MIT
Keywords: address book contact people
Platform: Linux
Platform: Windows
Platform: OSX
Platform: Unix
Platform: RaspberryPi
Classifier: Development Status :: 5 - Production/Stable
Classifier: Intended Audience :: End Users/Desktop
Classifier: Topic :: Office/Business
Classifier: License :: OSI Approved :: MIT License
Classifier: Programming Language :: Python :: 3 :: Only
Classifier: Operating System :: OS Independent
